CapCokor_dua/__init__.py
CapCokor_dua/cli.py
CapCokor_dua-1.2.4.dist-info/METADATA
CapCokor_dua-1.2.4.dist-info/WHEEL
CapCokor_dua-1.2.4.dist-info/entry_points.txt
CapCokor_dua-1.2.4.dist-info/top_level.txt
CapCokor_dua-1.2.4.dist-info/RECORD
